{"schema_version":1,"clinic":{"id":"47118823-9149-4a23-b3ff-567246f66271","name":"Dr. Józsa Eszter Gabriella — háziorvosi praxis","legal_name":"Neptun-Med Kft.","registry_id":"130095154","country":"HU","city":"Budakalász","region":"PEST","postal_code":"2011","address":"2011, Budakalász, Klisovác u. 6-8.","address_raw":"2011, Budakalász, Klisovác u. 6-8.","address_canonical":"2011, Budakalász, Klisovác u. 6-8.","address_key":"HU:2011:budakalasz:klisovac:utca:6:8","phone":"+3626340548","phone_raw":"26/340-548","website":null,"domain":null,"official_website":null,"official_domain":null,"official_website_confidence":0.0,"clinic_type":"unknown","funding":"unknown","lead_score":32,"contactability_score":0,"data_quality_score":15,"scrape_difficulty_score":8,"source_coverage_status":"unresolved","identity_status":"registry_seeded","identity_confidence":0.95,"outreach_eligibility":"suppressed"},"state":{"clinic_id":"47118823-9149-4a23-b3ff-567246f66271","status":"not_processed","version":0},"machine_status":"no_candidate","candidates":[],"professionals":[],"sources":[],"documents":[],"canonical_decisions":[]}