{"schema_version":1,"clinic":{"id":"4ca30393-5578-4b81-b0de-bad6b9112cb7","name":"Komárom Város Önkormányzata — háziorvosi praxis","legal_name":"Komárom Város Önkormányzata","registry_id":"110095012","country":"HU","city":"Komárom","region":"KOMÁROM-ESZTERGOM","postal_code":"2900","address":"2900, Komárom, Beöthy Zsolt u. 4.","phone":"+3634345915","website":"http://www.komarom.hu/","domain":"komarom.hu","official_website":null,"official_domain":null,"official_website_confidence":0.0,"clinic_type":"unknown","funding":"unknown","lead_score":32,"contactability_score":0,"data_quality_score":15,"scrape_difficulty_score":25,"source_coverage_status":"sources_unresolved","identity_status":"registry_seeded","identity_confidence":0.95,"outreach_eligibility":"suppressed"},"state":{"clinic_id":"4ca30393-5578-4b81-b0de-bad6b9112cb7","status":"not_processed","version":0},"machine_status":"no_candidate","candidates":[],"professionals":[],"sources":[{"url":"https://alapellatas.okfo.gov.hu/tajekoztato-a-tartosan-betoltetlen-haziorvosi-korzetekrol/","domain":"alapellatas.okfo.gov.hu","source_type":"government_listing","source_role":"government","ownership_status":"unverified","ownership_confidence":0.0,"useful":false,"has_email":false,"has_phone":false,"has_patient_channel":false,"reason":null},{"url":"https://www.neak.gov.hu/pfile/file?path=/letoltheto/altfin_dok/szerzodott_szolgaltatok/Betoltetlen_haziorvosi_szolgalatok&inline=true","domain":"neak.gov.hu","source_type":"government_listing","source_role":"government","ownership_status":"unverified","ownership_confidence":0.0,"useful":false,"has_email":false,"has_phone":false,"has_patient_channel":false,"reason":null},{"url":"http://www.komarom.hu/","domain":"komarom.hu","source_type":"provider_domain_candidate","source_role":"official_candidate","ownership_status":"unverified","ownership_confidence":0.0,"useful":false,"has_email":false,"has_phone":false,"has_patient_channel":false,"reason":null},{"url":"https://merce.hu/2019/07/11/tovabb-nott-a-tartosan-betoltetlen-haziorvosi-praxisok-szama/","domain":"merce.hu","source_type":"provider_domain_candidate","source_role":"official_candidate","ownership_status":"unverified","ownership_confidence":0.0,"useful":false,"has_email":false,"has_phone":false,"has_patient_channel":false,"reason":null},{"url":"https://www.forbes.hu/uzlet/egeszsegugy-betegseg-korona-haziorvos/","domain":"forbes.hu","source_type":"provider_domain_candidate","source_role":"official_candidate","ownership_status":"unverified","ownership_confidence":0.0,"useful":false,"has_email":false,"has_phone":false,"has_patient_channel":false,"reason":null},{"url":"https://www.gki.hu/wp-content/uploads/2021/07/Haziorvosi-ellatas-Magyarorszagon_junius.pdf","domain":"gki.hu","source_type":"provider_domain_candidate","source_role":"official_candidate","ownership_status":"unverified","ownership_confidence":0.0,"useful":false,"has_email":false,"has_phone":false,"has_patient_channel":false,"reason":null},{"url":"https://www.hirbalaton.hu/tartosan-betoltetlen-haziorvosi-korzetek-magyarhirlap-hu/","domain":"hirbalaton.hu","source_type":"provider_domain_candidate","source_role":"official_candidate","ownership_status":"unverified","ownership_confidence":0.0,"useful":false,"has_email":false,"has_phone":false,"has_patient_channel":false,"reason":null},{"url":"https://www.kemma.hu/kozelet-komarom-esztergom/2016/04/nyolc-betoltetlen-haziorvosi-praxis-van-a-megyeben","domain":"kemma.hu","source_type":"provider_domain_candidate","source_role":"official_candidate","ownership_status":"unverified","ownership_confidence":0.0,"useful":false,"has_email":false,"has_phone":false,"has_patient_channel":false,"reason":null},{"url":"https://www.penzcentrum.hu/egeszseg/20220118/kritikus-a-helyzet-rengeteg-haziorvosi-praxisok-betoltetlen-magyarorszagon-1121181","domain":"penzcentrum.hu","source_type":"provider_domain_candidate","source_role":"official_candidate","ownership_status":"unverified","ownership_confidence":0.0,"useful":false,"has_email":false,"has_phone":false,"has_patient_channel":false,"reason":null},{"url":"https://www.pharmindex-online.hu/szakmapolitika/hirek-cikkek/oriasi-utemben-fogytak-a-haziorvosok-az-elmult-ket-evben","domain":"pharmindex-online.hu","source_type":"provider_domain_candidate","source_role":"official_candidate","ownership_status":"unverified","ownership_confidence":0.0,"useful":false,"has_email":false,"has_phone":false,"has_patient_channel":false,"reason":null}],"documents":[],"canonical_decisions":[]}