{"schema_version":1,"clinic":{"id":"817c9fd6-a6b7-4a2c-82ff-963ce1410f32","name":"Dr. Komáromi Mónika — háziorvosi praxis","legal_name":"DR. KOMÁROMI ÉS TÁRSA Bt.","registry_id":"030090139","country":"HU","city":"Csátalja","region":"BÁCS-KISKUN","postal_code":"6523","address":"6523, Csátalja, Erzsébet u.4.","address_raw":"6523, Csátalja, Erzsébet u.4.","address_canonical":"6523, Csátalja, Erzsébet u.4.","address_key":"HU:6523:csatalja:erzsebet:utca:4","phone":"+3679361742","phone_raw":"+3679361742","website":"http://www.efi.bajakorhaz.hu/index.php/egyuttmukodo-haziorvosok","domain":"efi.bajakorhaz.hu","official_website":null,"official_domain":null,"official_website_confidence":0.0,"clinic_type":"unknown","funding":"unknown","lead_score":32,"contactability_score":0,"data_quality_score":15,"scrape_difficulty_score":29,"source_coverage_status":"sources_unresolved","identity_status":"registry_seeded","identity_confidence":0.95,"outreach_eligibility":"suppressed"},"state":{"clinic_id":"817c9fd6-a6b7-4a2c-82ff-963ce1410f32","status":"needs_review","version":0},"machine_status":"no_candidate","candidates":[],"professionals":[],"sources":[{"url":"https://foglaljorvost.hu/haziorvosok/dr-komaromi-monika/","domain":"foglaljorvost.hu","source_type":"booking_platform","source_role":"booking","ownership_status":"unverified","ownership_confidence":0.0,"useful":false,"has_email":false,"has_phone":false,"has_patient_channel":false,"reason":null},{"url":"https://doki.hu/orvos/dr-komaromi-monika-csatalja-1702","domain":"doki.hu","source_type":"healthcare_directory","source_role":"directory","ownership_status":"unverified","ownership_confidence":0.0,"useful":false,"has_email":false,"has_phone":false,"has_patient_channel":false,"reason":null},{"url":"https://mtaki.hu/orvos/dr-komaromi-monika-csatalja-1702","domain":"mtaki.hu","source_type":"healthcare_directory","source_role":"directory","ownership_status":"unverified","ownership_confidence":0.0,"useful":false,"has_email":false,"has_phone":false,"has_patient_channel":false,"reason":"Domain mtaki.hu has 782 recent failed or non-actionable attempts and no useful clinic contacts."},{"url":"https://www.orvosaim.hu/haziorvosok/dr-komaromi-monika-haziorvos-csatalja/","domain":"orvosaim.hu","source_type":"healthcare_directory","source_role":"directory","ownership_status":"unverified","ownership_confidence":0.0,"useful":false,"has_email":false,"has_phone":false,"has_patient_channel":false,"reason":null},{"url":"https://www.webbeteg.hu/keresok/orvos/2542/dr-komaromi-monika","domain":"webbeteg.hu","source_type":"healthcare_directory","source_role":"directory","ownership_status":"unverified","ownership_confidence":0.0,"useful":false,"has_email":false,"has_phone":false,"has_patient_channel":false,"reason":null},{"url":"https://xn--cstalja-iwa.cylex.hu/ceg-info/dr--kom%C3%A1romi-m%C3%B3nika-26056.html","domain":"xn--cstalja-iwa.cylex.hu","source_type":"business_directory","source_role":"directory","ownership_status":"unverified","ownership_confidence":0.0,"useful":false,"has_email":false,"has_phone":false,"has_patient_channel":false,"reason":null},{"url":"http://www.efi.bajakorhaz.hu/index.php/egyuttmukodo-haziorvosok","domain":"efi.bajakorhaz.hu","source_type":"provider_domain_candidate","source_role":"official_candidate","ownership_status":"unverified","ownership_confidence":0.0,"useful":false,"has_email":false,"has_phone":false,"has_patient_channel":false,"reason":"Exact URL recently failed or is terminal (no_actionable_contact)."},{"url":"https://csatalja.hu/egeszseg/","domain":"csatalja.hu","source_type":"provider_domain_candidate","source_role":"official_candidate","ownership_status":"unverified","ownership_confidence":0.0,"useful":false,"has_email":false,"has_phone":false,"has_patient_channel":false,"reason":null},{"url":"https://csatalja.hu/haziorvosi-tajekoztato/","domain":"csatalja.hu","source_type":"provider_domain_candidate","source_role":"official_candidate","ownership_status":"unverified","ownership_confidence":0.0,"useful":false,"has_email":false,"has_phone":false,"has_patient_channel":false,"reason":null}],"documents":[],"canonical_decisions":[]}