{"schema_version":1,"clinic":{"id":"856fc27d-f6c5-4c86-98ec-16a0675c3531","name":"Dr. Fazekas Mária — háziorvosi praxis","legal_name":"Meridián 19 KFT.","registry_id":"010092367","country":"HU","city":"Budapest IV. kerület","region":"BUDAPEST","postal_code":"1047","address":"1047, Budapest IV. kerület, LISZT FERENC U. 23/A","phone":"+3613692249","website":"https://mtaki.hu/orvos/dr-fazekas-maria-budapest-iv-kerulet-784","domain":"mtaki.hu","official_website":null,"official_domain":null,"official_website_confidence":0.0,"clinic_type":"primary_care","funding":"unknown","lead_score":43,"contactability_score":25,"data_quality_score":25,"scrape_difficulty_score":44,"source_coverage_status":"sources_unresolved","identity_status":"registry_seeded","identity_confidence":0.95,"outreach_eligibility":"suppressed"},"state":{"clinic_id":"856fc27d-f6c5-4c86-98ec-16a0675c3531","status":"needs_review","version":0},"machine_status":"candidate_needs_review","candidates":[{"id":"ced4ccb1-fbf1-438a-9410-b27258be68e6","value":"info@fazekaskozpont.hu","raw_value":null,"candidate_variants":[],"classification":"third_party","usable_contact":false,"confidence":0.9,"owner_name":"fazekaskozpont.com","owner_type":"unknown","contact_role":"unknown","associated_role":null,"association_type":"unverified","verification_status":"unverified","outreach_eligibility":"unknown","syntax_status":"unknown","mx_status":"unknown","deliverability_status":"unknown","source_url":"http://www.fazekaskozpont.com/","evidence":"Írjon nekünk","reason":"Cached replay source was not reliably matched to the target clinic.","page_context":["page"],"observed_at":"2026-07-15T00:23:38.025333","evidence_links":[{"id":"ced4ccb1-fbf1-438a-9410-b27258be68e6:ef2723b1-f10b-4962-ba80-462ef91e37fe","contact_point_id":"ced4ccb1-fbf1-438a-9410-b27258be68e6","source_document_id":"ef2723b1-f10b-4962-ba80-462ef91e37fe","source_url":"https://www.fazekaskozpont.com/","title":"Dr. Kresz Mária Alapítvány | Fazekas Központ | Magyarország","observed_at":"2026-07-15T00:23:27.368313","exact_quote":"info@fazekaskozpont.hu","prefix_text":":\"https://www.fazekaskozpont.com\"}]\n\nCONTACT_CONTEXTS:\n[{\"kind\":\"phone\",\"value\":\"+36 14071502\",\"context\":\"{\\\"@context\\\": \\\"https://schema.org/\\\", \\\"@type\\\": \\\"LocalBusiness\\\", \\\"name\\\": \\\"Dr Kresz Mária Alapítvány\\\", \\\"url\\\": \\\"https://www.fazekaskozpont.com\\\", \\\"image\\\": \\\"https://static.wixstatic.com/media/7a3960_92020566dd1a42958091dab4895657f4~mv2.png\\\", \\\"address\\\": {\\\"@type\\\": \\\"PostalAddress\\\", \\\"addressCountry\\\": \\\"HU\\\", \\\"addressLocality\\\": \\\"Budapest\\\", \\\"addressRegion\\\": \\\"Budapest\\\", \\\"postalCode\\\": \\\"1164\\\", \\\"streetAddress\\\": \\\"72 Vidámvásár utca\\\"}, \\\"telephone\\\": \\\"+36 14071502\\\"}\",\"page_context\":[\"page\"],\"owner_name_hint\":\"Dr Kresz Mária Alapítvány\",\"owner_type_hint\":\"clinic\",\"structured_path\":\"json_ld[0].telephone\",\"raw_value\":null,\"candidate_variants\":[],\"deobfuscation_status\":\"not_obfuscated\"},{\"kind\":\"email\",\"value\":\"","suffix_text":"\",\"context\":\"Írjon nekünk\",\"page_context\":[\"page\"],\"owner_name_hint\":null,\"owner_type_hint\":null,\"structured_path\":null,\"raw_value\":null,\"candidate_variants\":[],\"deobfuscation_status\":\"not_obfuscated\"},{\"kind\":\"phone\",\"value\":\"003614071502\",\"context\":\"Hívjon bennünket!\",\"page_context\":[\"page\"],\"owner_name_hint\":null,\"owner_type_hint\":null,\"structured_path\":null,\"raw_value\":null,\"candidate_variants\":[],\"deobfuscation_status\":\"not_obfuscated\"}]\n\nÜdvözöljük a\nDr. Kresz Mária Alapítvány\nFazekas Központ honlapján\nAlapítványunkat Dr. Kresz Mária elképzelése alapján a Kárpát-medence hagyományos kultúrájának, a fazekasművészetnek dokumentálására, népszerűsítésére, hagyományainak ápolására és ismeretterjesztésre alakítottuk meg a néprajz és hozzá szorosan kapcsolódó tudományágak területére.\nAz Alapítványról\n1991 decemberében azzal a szándékkal jöt","char_start":1460,"char_end":1482,"evidence_kind":"retained_text_exact_match","open_url":"https://www.fazekaskozpont.com/"}]}],"professionals":[],"sources":[{"url":"https://foglaljorvost.hu/haziorvosok/dr-fazekas-maria/","domain":"foglaljorvost.hu","source_type":"booking_platform","source_role":"booking","ownership_status":"unverified","ownership_confidence":0.0,"useful":false,"has_email":false,"has_phone":false,"has_patient_channel":false,"reason":null},{"url":"https://budapest.cylex.hu/iv--kerulet--ujpest/h%C3%A1ziorvosi+rendel%C3%A9s-2.html","domain":"budapest.cylex.hu","source_type":"business_directory","source_role":"directory","ownership_status":"unverified","ownership_confidence":0.0,"useful":false,"has_email":false,"has_phone":false,"has_patient_channel":false,"reason":null},{"url":"https://dev.medgo.hu/item/felnott-haziorvos/budapest-iv-kerulet/dr-fazekas-maria/641","domain":"dev.medgo.hu","source_type":"healthcare_directory","source_role":"directory","ownership_status":"unverified","ownership_confidence":0.0,"useful":false,"has_email":false,"has_phone":false,"has_patient_channel":false,"reason":null},{"url":"https://doki.hu/orvos/dr-fazekas-maria-budapest-iv-kerulet-784","domain":"doki.hu","source_type":"healthcare_directory","source_role":"directory","ownership_status":"unverified","ownership_confidence":0.0,"useful":false,"has_email":false,"has_phone":false,"has_patient_channel":false,"reason":null},{"url":"https://doki.hu/telepules/budapest-iv-kerulet","domain":"doki.hu","source_type":"healthcare_directory","source_role":"directory","ownership_status":"unverified","ownership_confidence":0.0,"useful":false,"has_email":false,"has_phone":false,"has_patient_channel":false,"reason":null},{"url":"https://medgo.hu/item/felnott-haziorvos/budapest-iv-kerulet/dr-fazekas-maria/641","domain":"medgo.hu","source_type":"healthcare_directory","source_role":"directory","ownership_status":"unverified","ownership_confidence":0.0,"useful":false,"has_email":false,"has_phone":false,"has_patient_channel":false,"reason":null},{"url":"https://mtaki.hu/orvos/dr-fazekas-maria-budapest-iv-kerulet-784","domain":"mtaki.hu","source_type":"healthcare_directory","source_role":"directory","ownership_status":"unverified","ownership_confidence":0.0,"useful":false,"has_email":false,"has_phone":false,"has_patient_channel":false,"reason":"Domain mtaki.hu has 1743 recent failed or non-actionable attempts and no useful clinic contacts."},{"url":"https://www.orvosaim.hu/haziorvosok/dr-fazekas-maria-haziorvos-budapest/","domain":"orvosaim.hu","source_type":"healthcare_directory","source_role":"directory","ownership_status":"unverified","ownership_confidence":0.0,"useful":false,"has_email":false,"has_phone":false,"has_patient_channel":false,"reason":null},{"url":"http://www.ugykr.hu/","domain":"ugykr.hu","source_type":"provider_domain_candidate","source_role":"municipality","ownership_status":"unverified","ownership_confidence":0.0,"useful":false,"has_email":false,"has_phone":false,"has_patient_channel":false,"reason":"Supporting source lacks enough target-specific evidence."},{"url":"https://ujpest.hu/","domain":"ujpest.hu","source_type":"provider_domain_candidate","source_role":"municipality","ownership_status":"unverified","ownership_confidence":0.0,"useful":false,"has_email":false,"has_phone":false,"has_patient_channel":false,"reason":"Source contains no actionable contact owned by or explicitly associated with the provider."},{"url":"http://www.fazekaskozpont.com/","domain":"fazekaskozpont.com","source_type":"provider_domain_candidate","source_role":"official_candidate","ownership_status":"unverified","ownership_confidence":0.0,"useful":false,"has_email":false,"has_phone":false,"has_patient_channel":false,"reason":"Source contains no actionable contact owned by or explicitly associated with the provider."},{"url":"https://ketfarkukutya.mkkp.party/2023/07/17/ujpesti-haziorvosi-korzetek-terkepen/","domain":"ketfarkukutya.mkkp.party","source_type":"provider_domain_candidate","source_role":"official_candidate","ownership_status":"unverified","ownership_confidence":0.0,"useful":false,"has_email":false,"has_phone":false,"has_patient_channel":false,"reason":null}],"documents":[{"id":"772412db-b957-4233-beb6-9da31514abe3","source_url":"https://ujpest.hu/rendeletek_listaja/","final_url":"https://ujpest.hu/rendeletek_listaja/","title":"Rendeletek","provider":"direct","status":"saved","http_status":200,"content_type":"text/html","text_chars":19887,"truncated":false,"observed_at":"2026-07-15T17:02:29.052326"},{"id":"ef2723b1-f10b-4962-ba80-462ef91e37fe","source_url":"http://www.fazekaskozpont.com/","final_url":"https://www.fazekaskozpont.com/","title":"Dr. Kresz Mária Alapítvány | Fazekas Központ | Magyarország","provider":"scrapfly","status":"saved","http_status":200,"content_type":"text/html","text_chars":12961,"truncated":false,"observed_at":"2026-07-15T00:23:27.368313"}],"canonical_decisions":[]}