{"schema_version":1,"clinic":{"id":"a99639f9-5d46-400c-86de-f62fb0b03f80","name":"Dr. Svéda Melinda — háziorvosi praxis","legal_name":"MELAMED Kft.","registry_id":"150095001","country":"HU","city":"Balkány","region":"SZABOLCS-SZATMÁR-BEREG","postal_code":"4233","address":"4233, Balkány, Rákóczi u. 2.","address_raw":"4233, Balkány, Rákóczi u. 2.","address_canonical":"4233, Balkány, Rákóczi u. 2.","address_key":"HU:4233:balkany:rakoczi:utca:2","phone":"+3642561090","phone_raw":"(42)561-090","website":null,"domain":null,"official_website":null,"official_domain":null,"official_website_confidence":0.0,"clinic_type":"unknown","funding":"unknown","lead_score":32,"contactability_score":0,"data_quality_score":15,"scrape_difficulty_score":11,"source_coverage_status":"sources_unresolved","identity_status":"registry_seeded","identity_confidence":0.95,"outreach_eligibility":"suppressed"},"state":{"clinic_id":"a99639f9-5d46-400c-86de-f62fb0b03f80","status":"needs_review","version":0},"machine_status":"no_candidate","candidates":[],"professionals":[],"sources":[{"url":"http://www.balkany.hu/","domain":"balkany.hu","source_type":"provider_domain_candidate","source_role":"official_candidate","ownership_status":"unverified","ownership_confidence":0.0,"useful":false,"has_email":false,"has_phone":false,"has_patient_channel":false,"reason":"Supporting source lacks enough target-specific evidence."}],"documents":[{"id":"bc53c885-4af5-4395-9bb0-eddd7cd5077b","source_url":"http://www.balkany.hu/","final_url":"http://www.balkany.hu/","title":"Balkány Város Önkormányzata","provider":"scrapfly","status":"saved","http_status":200,"content_type":"text/html","text_chars":3782,"truncated":false,"raw_html_path":"sources/raw_html/hu/e563a88a0e381bda891ea18e5ee2180debdd7964a231a600dc9c989bbe9a5cba.html","review_text_path":null,"screenshot_path":null,"presentation_kind":"archived_html","observed_at":"2026-07-17T01:27:11.573024"}],"canonical_decisions":[]}